splintegrate/__init__.py
splintegrate/splintegrate.py
splintegrate-0.1.4.data/scripts/quick_split
splintegrate-0.1.4.dist-info/AUTHORS.rst
splintegrate-0.1.4.dist-info/LICENSE
splintegrate-0.1.4.dist-info/METADATA
splintegrate-0.1.4.dist-info/WHEEL
splintegrate-0.1.4.dist-info/top_level.txt
splintegrate-0.1.4.dist-info/RECORD
