Metadata-Version: 2.1
Name: splintegrate
Version: 0.1.4
Summary: Splintegrate splits and combines integrations up.
Home-page: https://github.com/eas342/splintegrate
Author: Everett Schlawin
Author-email: granfalloontoyballoon@hotmail.com
License: MIT license
Keywords: splintegrate
Classifier: Development Status :: 2 - Pre-Alpha
Classifier: Intended Audience :: Developers
Classifier: License :: OSI Approved :: MIT License
Classifier: Natural Language :: English
Classifier: Programming Language :: Python :: 3
Classifier: Programming Language :: Python :: 3.5
Classifier: Programming Language :: Python :: 3.6
Classifier: Programming Language :: Python :: 3.7
Classifier: Programming Language :: Python :: 3.8
Requires-Python: >=3.5
License-File: LICENSE
License-File: AUTHORS.rst
Requires-Dist: astropy (>2)
Requires-Dist: tqdm
